strongtyping_pyoverload/__init__.py
strongtyping_pyoverload/class_tools.py
tests/__init__.py
tests/module_based_test_file.py
tests/test_override.py
strongtyping_pyoverload-0.4.1.dist-info/METADATA
strongtyping_pyoverload-0.4.1.dist-info/WHEEL
strongtyping_pyoverload-0.4.1.dist-info/top_level.txt
strongtyping_pyoverload-0.4.1.dist-info/RECORD
