Metadata-Version: 2.4
Name: strongtyping-pyoverload
Version: 0.4.1
Summary: A Runtime method overload decorator.
Home-page: https://strongtyping-pyoverload.readthedocs.io/en/latest/
Author: FelixTheC
Author-email: fberndt87@gmail.com
License: MIT
Classifier: License :: OSI Approved :: MIT License
Classifier: Programming Language :: Python :: 3.9
Classifier: Programming Language :: Python :: 3.10
Classifier: Programming Language :: Python :: 3.11
Classifier: Programming Language :: Python :: 3.12
Classifier: Programming Language :: Python :: 3.13
Requires-Python: >=3.9
Requires-Dist: strongtyping<=3.14,>=3.10,>=3.9
Dynamic: author
Dynamic: author-email
Dynamic: classifier
Dynamic: description
Dynamic: description-content-type
Dynamic: home-page
Dynamic: license
Dynamic: requires-dist
Dynamic: requires-python
Dynamic: summary
